plantree/__init__.py
plantree/config.py
plantree/main.py
projects/default/_NAME_/__init__.py
projects/default/_NAME_/main.py
plantree-0.2444.5.dist-info/METADATA
plantree-0.2444.5.dist-info/WHEEL
plantree-0.2444.5.dist-info/entry_points.txt
plantree-0.2444.5.dist-info/top_level.txt
plantree-0.2444.5.dist-info/RECORD
